moml/__init__.py
moml/core/__init__.py
moml/core/hierarchical_graph_coarsener.py
moml/core/molecular_feature_extraction.py
moml/core/molecular_graph_processor.py
moml/data/__init__.py
moml/data/data_loader.py
moml/data/dataset.py
moml/data/dataset_loader.py
moml/data/dataset_splitter.py
moml/data/datasets.py
moml/data/feature_transforms.py
moml/data/molecule_processors.py
moml/data/pfas_sdf_dataset.py
moml/data/pytorch_data_loader.py
moml/data/spice_dataset.py
moml/data/processors/process_chemical_data.py
moml/models/__init__.py
moml/models/mgnn/__init__.py
moml/models/mgnn/djmgnn.py
moml/models/mgnn/hmgnn.py
moml/models/mgnn/evaluation/__init__.py
moml/models/mgnn/evaluation/metrics.py
moml/models/mgnn/evaluation/predictor.py
moml/models/mgnn/training/__init__.py
moml/models/mgnn/training/callbacks.py
moml/models/mgnn/training/trainer.py
moml/pipeline/__init__.py
moml/pipeline/pipeline_orchestrator.py
moml/simulation/__init__.py
moml/simulation/molecular_dynamics/__init__.py
moml/simulation/molecular_dynamics/ensemble.py
moml/simulation/molecular_dynamics/equilibration.py
moml/simulation/molecular_dynamics/monitors.py
moml/simulation/molecular_dynamics/runner.py
moml/simulation/molecular_dynamics/builder/system_builder.py
moml/simulation/molecular_dynamics/config/__init__.py
moml/simulation/molecular_dynamics/config/schema.py
moml/simulation/molecular_dynamics/force_field/mapper.py
moml/simulation/molecular_dynamics/force_field/registry.py
moml/simulation/molecular_dynamics/force_field/validator.py
moml/simulation/molecular_dynamics/force_field/plugins/__init__.py
moml/simulation/molecular_dynamics/force_field/plugins/gac_v1/build.py
moml/simulation/molecular_dynamics/force_field/plugins/ix_sdb_v1/build.py
moml/simulation/molecular_dynamics/force_field/plugins/nf_polyamide_v1/build.py
moml/simulation/molecular_dynamics/force_field/plugins/ro_v1/build.py
moml/simulation/qm/parser/__init__.py
moml/simulation/qm/parser/orca_parser.py
moml/utils/__init__.py
moml_ca-0.1.1.dist-info/licenses/LICENSE
moml_ca-0.1.1.dist-info/METADATA
moml_ca-0.1.1.dist-info/WHEEL
moml_ca-0.1.1.dist-info/entry_points.txt
moml_ca-0.1.1.dist-info/top_level.txt
moml_ca-0.1.1.dist-info/RECORD
