Metadata-Version: 2.4
Name: moml-ca
Version: 0.1.1
Summary: Molecular Machine Learning for Chemical Applications - A comprehensive Python package for molecular representation learning and property prediction using Graph Neural Networks
Author-email: SAKETH11111 <sakethbaddam10@gmail.com>
License: MIT
Project-URL: Homepage, https://github.com/SAKETH11111/MoML-CA
Project-URL: Repository, https://github.com/SAKETH11111/MoML-CA
Project-URL: Issues, https://github.com/SAKETH11111/MoML-CA/issues
Keywords: molecular,machine learning,graph neural networks,chemistry,PFAS
Classifier: Development Status :: 3 - Alpha
Classifier: Intended Audience :: Science/Research
Classifier: License :: OSI Approved :: MIT License
Classifier: Operating System :: OS Independent
Classifier: Programming Language :: Python :: 3
Classifier: Programming Language :: Python :: 3.8
Classifier: Programming Language :: Python :: 3.9
Classifier: Programming Language :: Python :: 3.10
Classifier: Topic :: Scientific/Engineering :: Chemistry
Classifier: Topic :: Scientific/Engineering :: Artificial Intelligence
Requires-Python: >=3.8
License-File: LICENSE
Requires-Dist: numpy>=1.21.0
Requires-Dist: scipy>=1.7.0
Requires-Dist: pandas>=1.3.0
Requires-Dist: torch>=1.12.0
Requires-Dist: torch-geometric>=2.0.0
Requires-Dist: torch-scatter>=2.1.0
Requires-Dist: rdkit>=2022.03.1
Requires-Dist: openmm>=7.5.0
Requires-Dist: mdtraj>=1.9.5
Requires-Dist: MDAnalysis>=2.4.0
Requires-Dist: pdbfixer-wheel>=1.11.0
Requires-Dist: dask>=2022.2.0
Requires-Dist: distributed>=2022.2.0
Requires-Dist: pyyaml>=6.0
Requires-Dist: python-json-logger>=2.0.0
Requires-Dist: matplotlib>=3.5.0
Requires-Dist: seaborn>=0.11.0
Requires-Dist: scikit-learn>=1.0.0
Requires-Dist: networkx>=2.6.0
Requires-Dist: plotly>=5.3.0
Requires-Dist: h5py>=3.6.0
Requires-Dist: luigi>=3.0.0
Requires-Dist: mlflow>=2.0.0
Requires-Dist: tqdm>=4.62.0
Provides-Extra: dev
Requires-Dist: pytest>=7.0.0; extra == "dev"
Requires-Dist: pytest-cov>=3.0.0; extra == "dev"
Requires-Dist: black>=21.12b0; extra == "dev"
Requires-Dist: flake8>=4.0.0; extra == "dev"
Requires-Dist: isort>=5.10.0; extra == "dev"
Provides-Extra: ff
Requires-Dist: openff-toolkit>=0.11.0; extra == "ff"
Dynamic: license-file
